Metadata-Version: 1.2
Name: pyjdbcconnector
Version: 0.1.4
Summary: A high level JDBC API
Home-page: https://github.com/DanWertheimer/pyJDBCConnector
Author: Daniel Wertheimer
Author-email: danwertheimer@gmail.com
License: MIT
Download-URL: https://github.com/DanWertheimer/pyJDBCConnector/archive/v0.1.4-alpha.tar.gz
Platform: UNKNOWN
Classifier: Development Status :: 3 - Alpha
Classifier: Intended Audience :: Developers
Classifier: License :: OSI Approved :: MIT License
Classifier: Programming Language :: Python :: 3.6
Requires-Python: >=3.6
